iboxstacksops/__init__.py
iboxstacksops/actions.py
iboxstacksops/aws.py
iboxstacksops/cfg.py
iboxstacksops/changeset.py
iboxstacksops/commands.py
iboxstacksops/dashboard.py
iboxstacksops/events.py
iboxstacksops/i_region.py
iboxstacksops/i_stack.py
iboxstacksops/msg.py
iboxstacksops/outputs.py
iboxstacksops/parameters.py
iboxstacksops/parser.py
iboxstacksops/replica.py
iboxstacksops/resolve.py
iboxstacksops/resources.py
iboxstacksops/route53.py
iboxstacksops/ssm.py
iboxstacksops/stacks.py
iboxstacksops/table.py
iboxstacksops/tags.py
iboxstacksops/template.py
iboxstacksops/tools.py
iboxstacksops-1.1.3.data/scripts/ibox_stacksops.py
iboxstacksops.egg-info/PKG-INFO
iboxstacksops.egg-info/SOURCES.txt
iboxstacksops.egg-info/dependency_links.txt
iboxstacksops.egg-info/requires.txt
iboxstacksops.egg-info/top_level.txt
iboxstacksops-1.1.3.dist-info/LICENSE
iboxstacksops-1.1.3.dist-info/METADATA
iboxstacksops-1.1.3.dist-info/WHEEL
iboxstacksops-1.1.3.dist-info/top_level.txt
iboxstacksops-1.1.3.dist-info/RECORD
