Metadata-Version: 2.1
Name: iboxstacksops
Version: 1.1.3
Summary: AWS Infrastructure in a Box - Stacks management program
Home-page: https://github.com/mello7tre/AwsIBoxStackOps
Author: Mello
Author-email: mello+python@ankot.org
License: OSI Approved :: Open Software License 3.0 (OSL-3.0)
Classifier: Programming Language :: Python :: 3
Classifier: License :: OSI Approved :: Open Software License 3.0 (OSL-3.0)
Classifier: Operating System :: OS Independent
Requires-Python: >=3.7
License-File: LICENSE
Requires-Dist: PyYAML (==5.*,>=5)
Requires-Dist: boto3
Requires-Dist: prettytable
Requires-Dist: tqdm
